{
  "RecipeVersion": "1.0.0",
  "Kind": "survey",
  "Survey": {
    "Name": "ISC",
    "Reference": "survey-isc.json",
    "TaskName": "isc"
  },
  "Scores": [
    {
      "Name": "Total",
      "Description": "Total score for Impulsivity Scale for Children (ISC)",
      "Items": [
        "ISC01",
        "ISC02",
        "ISC03",
        "ISC04",
        "ISC05",
        "ISC06",
        "ISC07",
        "ISC08"
      ],
      "Method": "sum",
      "Range": {
        "min": 8,
        "max": 56
      }
    }
  ],
  "Psychometrics": {
    "Reliability": {
      "InternalConsistency": {
        "CronbachAlpha": null,
        "Note": "Add reliability data from validation studies"
      }
    },
    "Validity": {
      "Note": "Add validity evidence from original publication"
    }
  },
  "Usage": {
    "ScoringGuidelines": {
      "en": "Calculate total score by summing all items. Higher scores indicate higher levels of the measured construct.",
      "de": "Berechnen Sie den Gesamtscore durch Summierung aller Items. Höhere Werte bedeuten höhere Ausprägungen des gemessenen Konstrukts."
    },
    "InterpretationGuidelines": {
      "en": "Refer to original publication for interpretation guidelines and norms.",
      "de": "Siehe Originalpublikation für Interpretationsrichtlinien und Normen."
    }
  }
}